[
  { "name"       : "jasmin-eclib"
  , "repository" : "https://github.com/jasmin-lang/jasmin"
  , "branch"     : "main"
  , "subdir"     : "eclib"
  , "config"     : "tests.config"
  , "scenario"   : "jasmin"
  , "options"    : ""
  }

  ,

  { "name"       : "sha3"
  , "repository" : "https://gitlab.com/easycrypt/sha3"
  , "branch"     : "next"
  , "subdir"     : "."
  , "config"     : "config/tests.config"
  , "scenario"   : "sponge"
  , "options"    : "-jobs 1"
  }

  ,

  { "name"       : "cryptobox"
  , "repository" : "https://gitlab.com/fdupress/ec-cryptobox"
  , "branch"     : "next"
  , "subdir"     : "."
  , "config"     : "config/tests.config"
  , "scenario"   : "cryptobox"
  , "options"    : ""
  }

  ,

  { "name"       : "xsalsa20"
  , "repository" : "https://gitlab.com/fdupress/ec-xsalsa"
  , "branch"     : "master"
  , "subdir"     : "."
  , "config"     : "config/tests.config"
  , "scenario"   : "xsalsa"
  , "options"    : ""
  }

  ,

  { "name"       : "xmss-acai"
  , "repository" : "https://github.com/MM45/FV-XMSS-EC"
  , "branch"     : "master"
  , "subdir"     : "."
  , "config"     : "config/tests.config"
  , "scenario"   : "xmss-acai"
  , "options"    : ""
  }

  ,

  { "name"       : "xmss-fsai"
  , "repository" : "https://github.com/MM45/FV-XMSS-EC"
  , "branch"     : "master"
  , "subdir"     : "."
  , "config"     : "config/tests.config"
  , "scenario"   : "xmss-fsai"
  , "options"    : ""
  }

  ,

  { "name"       : "sphincsplus"
  , "repository" : "https://github.com/MM45/FV-SPHINCSPLUS-EC"
  , "branch"     : "master"
  , "subdir"     : "."
  , "config"     : "config/tests.config"
  , "scenario"   : "sphincsplus"
  , "options"    : ""
  }

  ,

  { "name"       : "curve25519"
  , "repository" : "https://github.com/formosa-crypto/formosa-25519"
  , "branch"     : "main"
  , "subdir"     : "proof/crypto_scalarmult/curve25519"
  , "config"     : "tests.config"
  , "scenario"   : "curve25519"
  , "options"    : ""
  }
]
